navium/__init__.py
navium/browser.py
navium/install.py
scripts/__init__.py
scripts/_http.py
scripts/exceptions.py
scripts/page.py
scripts/runtime.py
scripts/sockets.py
Navium-1.0.dist-info/LICENSE
Navium-1.0.dist-info/METADATA
Navium-1.0.dist-info/WHEEL
Navium-1.0.dist-info/entry_points.txt
Navium-1.0.dist-info/top_level.txt
Navium-1.0.dist-info/RECORD
