Metadata-Version: 2.1
Name: Navium
Version: 1.0
Summary: Navium is a Python-based automation library that leverages Chromium to control browser behavior, execute commands, and interact with web pages via WebSockets.
Author: Mohammad Hassan
License: MIT
Keywords: browser,automation,selenium,playwright,chromium,scraping,crawling,web,testing,navium
Platform: windows
Classifier: Programming Language :: Python :: 3
Classifier: License :: OSI Approved :: MIT License
Classifier: Operating System :: Microsoft :: Windows
License-File: LICENSE
Requires-Dist: cffi >=1.17.1
Requires-Dist: gevent >=24.2.1
Requires-Dist: pillow >=10.4.0
Requires-Dist: websocket-client >=1.8.0
Provides-Extra: websocket
Requires-Dist: greenlet >=3.1.1 ; extra == 'websocket'
Requires-Dist: zope.event >=5.0 ; extra == 'websocket'
Requires-Dist: zope.interface >=7.0.3 ; extra == 'websocket'
